taksa/__init__.py
taksa/configuration.py
taksa/dependency.py
taksa/manager.py
taksa/state.py
taksa-0.2.0.dist-info/licenses/LICENSE
tests/__init__.py
tests/test_cpp_cmake_dependency.py
taksa-0.2.0.dist-info/METADATA
taksa-0.2.0.dist-info/WHEEL
taksa-0.2.0.dist-info/top_level.txt
taksa-0.2.0.dist-info/RECORD
